cnvrg_extras/__init__.py
cnvrg_extras/_version.py
cnvrg_extras-0.0.1.dist-info/LICENSE
cnvrg_extras-0.0.1.dist-info/METADATA
cnvrg_extras-0.0.1.dist-info/WHEEL
cnvrg_extras-0.0.1.dist-info/top_level.txt
cnvrg_extras-0.0.1.dist-info/RECORD
