Metadata-Version: 2.1
Name: cnvrg-extras
Version: 0.0.1
Summary: cnvrg helper SDK
Home-page: https://github.com/nctiggy/cnvrg_extras
Author: Craig Smith
Author-email: craig.smith@cnvrg.io
License: UNKNOWN
Platform: UNKNOWN
Classifier: Programming Language :: Python :: 3
Classifier: License :: OSI Approved :: MIT License
Classifier: Operating System :: OS Independent
Requires-Python: >=3.6
License-File: LICENSE
Requires-Dist: cnvrgv2 (>=1.0.9)
